pypi_examiner/__init__.py
pypi_examiner/client.py
pypi_examiner-0.6.dist-info/LICENSE
pypi_examiner-0.6.dist-info/METADATA
pypi_examiner-0.6.dist-info/WHEEL
pypi_examiner-0.6.dist-info/top_level.txt
pypi_examiner-0.6.dist-info/RECORD
