Metadata-Version: 2.1
Name: pypi-examiner
Version: 0.6
Summary: A simple client to fetch the few things PyPI does not expose via API
Home-page: https://chris.partridge.tech/
Author: Chris Partridge
Author-email: tweedge-public@partridge.tech
License: Apache License 2.0
Project-URL: Source, https://github.com/tweedge/pypi-examiner
Classifier: Development Status :: 4 - Beta
Classifier: License :: OSI Approved :: Apache Software License
Classifier: Operating System :: MacOS
Classifier: Operating System :: Microsoft :: Windows
Classifier: Operating System :: POSIX :: Linux
Classifier: Programming Language :: Python
Classifier: Programming Language :: Python :: 3
Classifier: Programming Language :: Python :: 3.7
Classifier: Programming Language :: Python :: 3.8
Classifier: Programming Language :: Python :: 3.9
Classifier: Programming Language :: Python :: 3.10
License-File: LICENSE
Requires-Dist: requests-html
Requires-Dist: lxml-html-clean
